stl_reader/__init__.py
stl_reader/py.typed
stl_reader/reader.py
stl_reader/stl_reader.pyd
stl_reader/stl_reader.pyi
stl_reader-0.2.2.dist-info/METADATA
stl_reader-0.2.2.dist-info/WHEEL
stl_reader-0.2.2.dist-info/licenses/LICENSE
stl_reader-0.2.2.dist-info/RECORD
